setup.py
bin/lc3methodgen
lc3methodgen/__init__.py
lc3methodgen/method_generator.py
lc3methodgen.egg-info/PKG-INFO
lc3methodgen.egg-info/SOURCES.txt
lc3methodgen.egg-info/dependency_links.txt
lc3methodgen.egg-info/not-zip-safe
lc3methodgen.egg-info/requires.txt
lc3methodgen.egg-info/top_level.txt