Metadata-Version: 1.0
Name: lc3methodgen
Version: 1.0
Summary: LC3 Method Generator
Home-page: http://github.com/skyman/lc3methodgen
Author: Cem Gokmen
Author-email: cgokmen@gatech.edu
License: MIT
Platform: UNKNOWN
